{
  "brown sugar": 3.75,
  "butter": 7.14,
  "cocoa powder": 2.5,
  "egg": 5.13,
  "egg yolks": 28.0,
  "espresso powder": 0.09,
  "flour": 3.33,
  "g flour": 0.26,
  "oil": 8.67,
  "salt": 0,
  "sugar": 3.75,
  "vanilla": 2.49,
  "water": 0.42,
  "white sugar": 4.01,
  "whole chicken": 2.43,
  "all-purpose flour": 3.33,
  "almond extract": 2.88,
  "almond flour": 6.0,
  "almonds": 6.33,
  "avocado oil": 8.0,
  "bacon": 6.0,
  "balsamic vinegar": 0.67,
  "beans": 3.4,
  "beef": 1.29,
  "beef broth": 0.04,
  "black beans": 1.41,
  "bread": 1.46,
  "bread flour": 3.33,
  "broccoli": 0.24,
  "buttermilk": 0.43,
  "cake flour": 15.2,
  "canned tomatoes": 0.34,
  "canola oil": 9.0,
  "carrot": 0.44,
  "cauliflower": 0.24,
  "celery": 0.14,
  "cheddar": 3.93,
  "cherry tomatoes": 0.21,
  "chicken": 1.07,
  "chicken breast": 1.65,
  "chicken broth": 0.06,
  "chicken thighs": 2.41,
  "chickpeas": 1.28,
  "chocolate chips": 4.8,
  "clarified butter": 8.57,
  "cloves": 11.4,
  "coconut milk": 0.31,
  "coconut oil": 8.95,
  "coriander": 12.4,
  "corn": 0.56,
  "corn syrup": 2.83,
  "cornstarch": 3.81,
  "cream": 8.15,
  "cream cheese": 3.21,
  "crushed tomatoes": 0.33,
  "cumin": 15.7,
  "dark brown sugar": 3.75,
  "dark chocolate": 5.26,
  "dijon mustard": 1.0,
  "dill": 0.12,
  "dried cranberries": 3.34,
  "egg white": 0.55,
  "egg yolk": 28.0,
  "extra virgin olive oil": 8.0,
  "feta": 3.21,
  "fish sauce": 0.35,
  "flour tortilla": 2.79,
  "fresh ginger": 0.01,
  "garlic": 1.67,
  "garlic powder": 3.33,
  "ghee": 9.29,
  "ginger": 0,
  "ginger powder": 10.4,
  "granulated sugar": 3.75,
  "green onion": 0.32,
  "ground beef": 3.12,
  "ground pork": 3.12,
  "ground turkey": 2.05,
  "half and half": 1.33,
  "heavy cream": 3.33,
  "hoisin sauce": 2.2,
  "honey": 12.7,
  "instant yeast": 3.25,
  "jalapeño": 2.93,
  "jasmine rice": 3.6,
  "kale": 0.47,
  "ketchup": 1.09,
  "kidney beans": 1.0,
  "kosher salt": 0,
  "leek": 0.88,
  "lemon": 3.0,
  "light brown sugar": 3.75,
  "lime": 3.28,
  "maple syrup": 3.33,
  "marinara sauce": 0.5,
  "mayonnaise": 6.67,
  "milk": 0.55,
  "mirin": 3.0,
  "miso paste": 1.67,
  "molasses": 2.9,
  "mozzarella": 3.21,
  "mushroom": 0.8,
  "mustard": 0.69,
  "nutmeg": 37.0,
  "nuts": 4.0,
  "oats": 3.75,
  "olive oil": 9.0,
  "onion": 2.89,
  "oregano": 0,
  "oyster sauce": 0.51,
  "paprika": 0,
  "parmesan": 17.6,
  "parsley": 0,
  "pasta": 3.75,
  "pastry flour": 15.0,
  "peanut butter": 5.98,
  "peas": 0.56,
  "pecans": 7.0,
  "penne": 3.33,
  "pork": 1.18,
  "potato": 1.71,
  "powdered sugar": 3.85,
  "raisins": 2.99,
  "red onion": 0.3,
  "red pepper flakes": 0.55,
  "red wine": 0.85,
  "red wine vinegar": 0,
  "rice": 1.39,
  "rice vinegar": 0.24,
  "rice wine": 1.34,
  "rolled oats": 3.75,
  "rosemary": 0,
  "salmon": 1.39,
  "salted butter": 7.14,
  "sea salt": 0,
  "sesame oil": 8.84,
  "shallot": 3.01,
  "shredded coconut": 6.5,
  "shrimp": 0.47,
  "smoked paprika": 6.25,
  "sour cream": 2.0,
  "soy sauce": 0.53,
  "spaghetti": 3.75,
  "spinach": 0.21,
  "sriracha": 3.21,
  "steak": 5.56,
  "sweet potato": 1.06,
  "tahini": 6.97,
  "tamari": 0.33,
  "tomato paste": 0.91,
  "tomato sauce": 0.25,
  "tuna": 0.94,
  "turmeric": 0,
  "unsalted butter": 7.14,
  "vanilla extract": 2.88,
  "vegetable broth": 0.06,
  "vegetable oil": 8.57,
  "vinegar": 0.21,
  "walnuts": 6.56,
  "white chocolate": 5.52,
  "white onion": 1.48,
  "white pepper": 12.4,
  "white vinegar": 0,
  "white wine": 0.82,
  "whole milk": 0.67,
  "whole wheat flour": 3.67,
  "worcestershire sauce": 0.77,
  "yogurt": 0.94,
  "zucchini": 0.21,
  "apple": 0.52,
  "apricot": 0.53,
  "avocado": 4.27,
  "banana": 3.12,
  "blackberry": 0.25,
  "blood orange": 0.14,
  "blueberry": 2.5,
  "cantaloupe": 0.37,
  "cherry": 3.6,
  "clementine": 0.47,
  "coconut": 5.0,
  "cranberry": 0.5,
  "date": 2.82,
  "fig": 2.5,
  "grape": 0.54,
  "grapefruit": 0.45,
  "green apple": 4.0,
  "honeydew": 0.36,
  "kiwi": 0.61,
  "mango": 3.5,
  "nectarine": 0.43,
  "orange": 3.81,
  "papaya": 2.5,
  "passion fruit": 0.33,
  "peach": 4.11,
  "pear": 0.59,
  "plum": 0.46,
  "pomegranate": 0.48,
  "raspberry": 2.22,
  "strawberry": 0.85,
  "watermelon": 0.31,
  "active dry yeast": 13.6,
  "apple cider vinegar": 0.52,
  "baking powder": 1.05,
  "baking soda": 1.05,
  "basil": 1.5,
  "basmati rice": 1.48,
  "bay leaf": 3.13,
  "bell pepper": 14.7,
  "black pepper": 2.79,
  "breadcrumbs": 3.6,
  "cayenne": 1.5,
  "chili powder": 1.02,
  "chives": 1.5,
  "cilantro": 1.5,
  "cinnamon": 2.0,
  "hot sauce": 0.12,
  "italian seasoning": 2.59,
  "lemon juice": 3.0,
  "lime juice": 3.28,
  "mandarin": 1.5,
  "pineapple": 0.6,
  "red apple": 0.85,
  "thyme": 1.5,
  "tofu": 1.5,
  "tomato": 0.4
}